yeeducli/__init__.py
yeeducli/config.py
yeeducli/constants.py
yeeducli/yeedu.py
yeeducli/openapi/__init__.py
yeeducli/openapi/billing/__init__.py
yeeducli/openapi/billing/billing.py
yeeducli/openapi/catalog_explorer/__init__.py
yeeducli/openapi/catalog_explorer/catalog_explorer.py
yeeducli/openapi/cluster/__init__.py
yeeducli/openapi/cluster/cluster_configuration.py
yeeducli/openapi/cluster/cluster_instance.py
yeeducli/openapi/cluster/cluster_workspace_mapping.py
yeeducli/openapi/cluster/download_cluster_instance_logs.py
yeeducli/openapi/configure/__init__.py
yeeducli/openapi/configure/configure_user.py
yeeducli/openapi/iam/__init__.py
yeeducli/openapi/iam/common_platform_and_admin.py
yeeducli/openapi/iam/iam_lookup.py
yeeducli/openapi/iam/platform_admin.py
yeeducli/openapi/iam/shared_platform_and_admin.py
yeeducli/openapi/iam/user.py
yeeducli/openapi/job/__init__.py
yeeducli/openapi/job/download_job_instance_logs.py
yeeducli/openapi/job/spark_job_config.py
yeeducli/openapi/job/spark_job_instance.py
yeeducli/openapi/metastore_catalog/__init__.py
yeeducli/openapi/metastore_catalog/metastore_catalog.py
yeeducli/openapi/metastore_catalog/metastore_catalog_user_association.py
yeeducli/openapi/metastore_catalog/metastore_catalog_workspace_association.py
yeeducli/openapi/metastore_catalog/metstore_catalog_tenant_association.py
yeeducli/openapi/notebook/__init__.py
yeeducli/openapi/notebook/download_notebook_instance_logs.py
yeeducli/openapi/notebook/notebook_config.py
yeeducli/openapi/notebook/notebook_instance.py
yeeducli/openapi/resource/__init__.py
yeeducli/openapi/resource/boot_disk_image_configuration.py
yeeducli/openapi/resource/cloud_environment.py
yeeducli/openapi/resource/credentials_config.py
yeeducli/openapi/resource/hive_metastore_configuration.py
yeeducli/openapi/resource/lookup.py
yeeducli/openapi/resource/network_configuration.py
yeeducli/openapi/resource/object_storage_manager.py
yeeducli/openapi/resource/object_storage_manager_files.py
yeedu_cli-4.12.2.dist-info/METADATA
yeedu_cli-4.12.2.dist-info/WHEEL
yeedu_cli-4.12.2.dist-info/entry_points.txt
yeedu_cli-4.12.2.dist-info/top_level.txt
yeedu_cli-4.12.2.dist-info/RECORD
