Metadata-Version: 2.1
Name: yeedu-cli
Version: 4.12.2
Summary: Universal Command Line Interface for Yeedu.
Home-page: https://yeedu.io
Author: Yeedu
Author-email: yeedu@yeedu.io
License: All Rights Reserved
Requires-Python: >=3.8
Requires-Dist: argparse ==1.4.0
Requires-Dist: requests ==2.28.1
Requires-Dist: urllib3 <1.27,>=1.26.6
Requires-Dist: charset-normalizer <3.0,>=2.0
Requires-Dist: python-dotenv ==1.0.0
Requires-Dist: PyYAML <7.0,>=6.0.1
Requires-Dist: setuptools ==64
